dwarfgen/__init__.py
dwarfgen/__main__.py
dwarfgen/src/__init__.py
dwarfgen/src/codegen.py
dwarfgen/src/dwarfgen.py
dwarfgen/src/enumeration.py
dwarfgen/src/idlgenerator.py
dwarfgen/src/member.py
dwarfgen/src/namespace.py
dwarfgen/src/structure.py
dwarfgen/src/union.py
dwarfgen/src/lang_generators/__init__.py
dwarfgen/src/lang_generators/cpp.py
dwarfgen-0.3.dist-info/LICENSE
dwarfgen-0.3.dist-info/METADATA
dwarfgen-0.3.dist-info/WHEEL
dwarfgen-0.3.dist-info/top_level.txt
dwarfgen-0.3.dist-info/RECORD
