Metadata-Version: 2.1
Name: dwarfgen
Version: 0.3
Summary: IDL/Code generation utility
Home-page: https://github.com/claybrooks/dwarfgen
Author: Clay Brooks
Author-email: clay_brooks@outlook.com
License: UNKNOWN
Platform: UNKNOWN
Classifier: Programming Language :: Python :: 3
Classifier: License :: OSI Approved :: The Unlicense (Unlicense)
Classifier: Operating System :: OS Independent
Requires-Dist: pyelftools
Requires-Dist: pymanifest
